kombu_pyamqp_threadsafe/__init__.py
kombu_pyamqp_threadsafe/producer.py
kombu_pyamqp_threadsafe/simple.py
kombu_pyamqp_threadsafe-0.6.2.dist-info/METADATA
kombu_pyamqp_threadsafe-0.6.2.dist-info/WHEEL
kombu_pyamqp_threadsafe-0.6.2.dist-info/licenses/LICENSE
kombu_pyamqp_threadsafe-0.6.2.dist-info/RECORD
