Metadata-Version: 2.4
Name: kombu-pyamqp-threadsafe
Version: 0.6.2
Summary: Threadsafe implementation of pyamqp transport for kombu
License-File: LICENSE
Author: spumer
Author-email: john@example.com
Requires-Python: >=3.10,<4.0
Classifier: Programming Language :: Python :: 3
Classifier: Programming Language :: Python :: 3.10
Classifier: Programming Language :: Python :: 3.11
Classifier: Programming Language :: Python :: 3.12
Classifier: Programming Language :: Python :: 3.13
Classifier: Programming Language :: Python :: 3.14
Requires-Dist: kombu (>=5.6.1,<6.0.0)
Project-URL: Repository, https://github.com/spumer/kombu-pyamqp-threadsafe
